{
  "OwnIdSdkDefault" : {
    "Email" : "E-posta",
    "First Name" : "Ad",
    "Last Name" : "Soyadı",
    "Nickname" : "Takma ad",
    "Field {0} is required" : "Alan {0} gerekli",
    "Field {0} has incorrect format" : "Alan {0} yanlış biçim içeriyor",
    "The field {0} must be a string or array type with a maximum length of '{1}'" : "{0} alanı, en fazla '{1}' uzunluğunda bir dizi veya dizilim türü olmalıdır",
    "Error_PhoneAlreadyConnected" : "Telefonunuz zaten bir hesapla ilişkilendirilmiş, lütfen oturum açma sayfasına gidin",
    "Error_UserNotFound" : "Kullanıcı bulunamadı",
    "Error_RequiresBiometricInput" : "Biyometrik giriş gerekli",
    "Error_RecoveryTokenExpired" : "Kurtarma simgesinin süresi doldu",
    "Error_UserCanceledAuth" : "Yetkilendirme süreci kullanıcı tarafından iptal edildi",
    "Email_MagicLink_Body" : "<!DOCTYPE html><html><head><style> body {font-family: 72;font-style: normal;font-weight: normal;font-size: 14px;line-height: 24px;} div {margin-bottom: 20px;} .rounded-link {background: #0070F2;color: #FFFFFF!important;display: block;padding: 8px 26px;text-align: center;text-decoration: none;border-radius: 4px;font-weight: bold;width: auto;}</style></head><body><div>Merhaba {userName},<br>Hesabınızda oturum açmak için aşağıdaki bağlantıya tıklayın.</div><div style=\"display: flex\"><a target=\"_blank\" class=\"rounded-link\" href=\"{link}\">Sihirli bağlantınız</a></div><div>Güvenlik nedeniyle, bu bağlantı yalnızca bu talebi başlatan aynı tarayıcıda geçerli olacaktır. Yukarıdaki bağlantı çalışmazsa aşağıdaki URL'yi kopyalayıp tarayıcıya yapıştırmayı deneyin:<br/>{link}</div><div>Bu sihirli bağlantıyı siz talep etmediyseniz bu e-postayı dikkate almayın.</div></body></html>",
    "Email_MagicLink_Subject" : "{0} için sihirli bağlantı"
  }
}
